{
  "parent": "minecraft:recipes/root",
  "criteria": {
    "has_the_recipe": {
      "conditions": {
        "recipe": "realearthores:planks_citrus_from_wood_citrus_stripped"
      },
      "trigger": "minecraft:recipe_unlocked"
    },
    "has_wood_citrus_stripped": {
      "conditions": {
        "items": [
          {
            "items": [
              "realearthores:wood_citrus_stripped"
            ]
          }
        ]
      },
      "trigger": "minecraft:inventory_changed"
    }
  },
  "requirements": [
    [
      "has_wood_citrus_stripped",
      "has_the_recipe"
    ]
  ],
  "rewards": {
    "recipes": [
      "realearthores:planks_citrus_from_wood_citrus_stripped"
    ]
  },
  "sends_telemetry_event": false
}